<annotation>
    <folder>image_cleaned</folder>
    <filename>operating139.jpg</filename>
    <size>
        <width>800</width>
        <height>533</height>
        <depth>3</depth>
    </size>
    <object>
        <name>surgical_light</name>
        <difficult>0</difficult>
        <bndbox>
            <xmin>523</xmin>
            <ymin>20</ymin>
            <xmax>670</xmax>
            <ymax>121</ymax>
        </bndbox>
    </object>
    <object>
        <name>surgical_light</name>
        <difficult>0</difficult>
        <bndbox>
            <xmin>220</xmin>
            <ymin>18</ymin>
            <xmax>318</xmax>
            <ymax>147</ymax>
        </bndbox>
    </object>
    <object>
        <name>bedside_monitor</name>
        <difficult>0</difficult>
        <bndbox>
            <xmin>329</xmin>
            <ymin>137</ymin>
            <xmax>392</xmax>
            <ymax>193</ymax>
        </bndbox>
    </object>
    <object>
        <name>breathing_tube</name>
        <difficult>0</difficult>
        <bndbox>
            <xmin>571</xmin>
            <ymin>254</ymin>
            <xmax>682</xmax>
            <ymax>491</ymax>
        </bndbox>
    </object>
    <object>
        <name>ventilator</name>
        <difficult>0</difficult>
        <bndbox>
            <xmin>570</xmin>
            <ymin>143</ymin>
            <xmax>800</xmax>
            <ymax>533</ymax>
        </bndbox>
    </object>
    <object>
        <name>utility_cart</name>
        <difficult>0</difficult>
        <bndbox>
            <xmin>478</xmin>
            <ymin>273</ymin>
            <xmax>628</xmax>
            <ymax>366</ymax>
        </bndbox>
    </object>
    <object>
        <name>waste_bin</name>
        <difficult>0</difficult>
        <bndbox>
            <xmin>269</xmin>
            <ymin>282</ymin>
            <xmax>308</xmax>
            <ymax>313</ymax>
        </bndbox>
    </object>
    <object>
        <name>operating_bed</name>
        <difficult>0</difficult>
        <bndbox>
            <xmin>235</xmin>
            <ymin>307</ymin>
            <xmax>622</xmax>
            <ymax>533</ymax>
        </bndbox>
    </object>
    <object>
        <name>electrosurgical_unit</name>
        <difficult>0</difficult>
        <bndbox>
            <xmin>329</xmin>
            <ymin>251</ymin>
            <xmax>395</xmax>
            <ymax>274</ymax>
        </bndbox>
    </object>
</annotation>