<annotation>
    <folder>image</folder>
    <filename>image_1023.jpg</filename>
    <size>
        <width>1280</width>
        <height>720</height>
        <depth>3</depth>
    </size>
    <object>
        <name>staff</name>
        <difficult>0</difficult>
        <bndbox>
            <xmin>151.000000</xmin>
            <ymin>40.000000</ymin>
            <xmax>598.000000</xmax>
            <ymax>718.000000</ymax>
        </bndbox>
    </object>
    <object>
        <name>computer</name>
        <difficult>0</difficult>
        <bndbox>
            <xmin>1.000000</xmin>
            <ymin>148.000000</ymin>
            <xmax>138.000000</xmax>
            <ymax>326.000000</ymax>
        </bndbox>
    </object>
    <object>
        <name>mouse</name>
        <difficult>0</difficult>
        <bndbox>
            <xmin>71.000000</xmin>
            <ymin>400.000000</ymin>
            <xmax>129.000000</xmax>
            <ymax>424.000000</ymax>
        </bndbox>
    </object>
    <object>
        <name>hospital_bed</name>
        <difficult>0</difficult>
        <bndbox>
            <xmin>8.000000</xmin>
            <ymin>418.000000</ymin>
            <xmax>1113.000000</xmax>
            <ymax>720.000000</ymax>
        </bndbox>
    </object>
    <object>
        <name>patient</name>
        <difficult>0</difficult>
        <bndbox>
            <xmin>558.000000</xmin>
            <ymin>489.000000</ymin>
            <xmax>809.000000</xmax>
            <ymax>580.000000</ymax>
        </bndbox>
    </object>
    <object>
        <name>bedrail</name>
        <difficult>0</difficult>
        <bndbox>
            <xmin>7.000000</xmin>
            <ymin>440.000000</ymin>
            <xmax>665.000000</xmax>
            <ymax>718.000000</ymax>
        </bndbox>
    </object>
    <object>
        <name>curtain</name>
        <difficult>0</difficult>
        <bndbox>
            <xmin>1.000000</xmin>
            <ymin>1.000000</ymin>
            <xmax>96.000000</xmax>
            <ymax>150.000000</ymax>
        </bndbox>
    </object>
</annotation>