<annotation>
    <folder>image_cleaned</folder>
    <filename>Texas Children's Hospital Medical Center Campus Tour 140.jpg</filename>
    <size>
        <width>1280</width>
        <height>720</height>
        <depth>3</depth>
    </size>
    <object>
        <name>chair</name>
        <difficult>0</difficult>
        <bndbox>
            <xmin>189</xmin>
            <ymin>437</ymin>
            <xmax>367</xmax>
            <ymax>663</ymax>
        </bndbox>
    </object>
    <object>
        <name>chair</name>
        <difficult>0</difficult>
        <bndbox>
            <xmin>2</xmin>
            <ymin>450</ymin>
            <xmax>225</xmax>
            <ymax>720</ymax>
        </bndbox>
    </object>
    <object>
        <name>sofa</name>
        <difficult>0</difficult>
        <bndbox>
            <xmin>834</xmin>
            <ymin>464</ymin>
            <xmax>1154</xmax>
            <ymax>720</ymax>
        </bndbox>
    </object>
    <object>
        <name>chair</name>
        <difficult>0</difficult>
        <bndbox>
            <xmin>1125</xmin>
            <ymin>427</ymin>
            <xmax>1223</xmax>
            <ymax>582</ymax>
        </bndbox>
    </object>
    <object>
        <name>waste_bin</name>
        <difficult>0</difficult>
        <bndbox>
            <xmin>690</xmin>
            <ymin>389</ymin>
            <xmax>746</xmax>
            <ymax>487</ymax>
        </bndbox>
    </object>
    <object>
        <name>table</name>
        <difficult>0</difficult>
        <bndbox>
            <xmin>1195</xmin>
            <ymin>462</ymin>
            <xmax>1280</xmax>
            <ymax>643</ymax>
        </bndbox>
    </object>
</annotation>