<annotation>
    <folder>image_cleaned</folder>
    <filename>The new Humber River Hospital Mock Up Room Video Tour 348.jpg</filename>
    <size>
        <width>1280</width>
        <height>720</height>
        <depth>3</depth>
    </size>
    <object>
        <name>bedside_table</name>
        <difficult>0</difficult>
        <bndbox>
            <xmin>284</xmin>
            <ymin>341</ymin>
            <xmax>366</xmax>
            <ymax>436</ymax>
        </bndbox>
    </object>
    <object>
        <name>bedrail</name>
        <difficult>0</difficult>
        <bndbox>
            <xmin>326</xmin>
            <ymin>301</ymin>
            <xmax>448</xmax>
            <ymax>405</ymax>
        </bndbox>
    </object>
    <object>
        <name>bedrail</name>
        <difficult>0</difficult>
        <bndbox>
            <xmin>546</xmin>
            <ymin>333</ymin>
            <xmax>657</xmax>
            <ymax>478</ymax>
        </bndbox>
    </object>
    <object>
        <name>bedrail</name>
        <difficult>0</difficult>
        <bndbox>
            <xmin>136</xmin>
            <ymin>460</ymin>
            <xmax>564</xmax>
            <ymax>714</ymax>
        </bndbox>
    </object>
    <object>
        <name>dispenser</name>
        <difficult>0</difficult>
        <bndbox>
            <xmin>959</xmin>
            <ymin>131</ymin>
            <xmax>1167</xmax>
            <ymax>241</ymax>
        </bndbox>
    </object>
    <object>
        <name>dispenser</name>
        <difficult>0</difficult>
        <bndbox>
            <xmin>1049</xmin>
            <ymin>248</ymin>
            <xmax>1130</xmax>
            <ymax>352</ymax>
        </bndbox>
    </object>
    <object>
        <name>medical_waste_container</name>
        <difficult>0</difficult>
        <bndbox>
            <xmin>341</xmin>
            <ymin>223</ymin>
            <xmax>394</xmax>
            <ymax>293</ymax>
        </bndbox>
    </object>
    <object>
        <name>dispenser</name>
        <difficult>0</difficult>
        <bndbox>
            <xmin>317</xmin>
            <ymin>208</ymin>
            <xmax>351</xmax>
            <ymax>260</ymax>
        </bndbox>
    </object>
    <object>
        <name>dispenser</name>
        <difficult>0</difficult>
        <bndbox>
            <xmin>305</xmin>
            <ymin>152</ymin>
            <xmax>377</xmax>
            <ymax>207</ymax>
        </bndbox>
    </object>
    <object>
        <name>iv_pole</name>
        <difficult>0</difficult>
        <bndbox>
            <xmin>495</xmin>
            <ymin>259</ymin>
            <xmax>529</xmax>
            <ymax>357</ymax>
        </bndbox>
    </object>
    <object>
        <name>medical_waste_container</name>
        <difficult>0</difficult>
        <bndbox>
            <xmin>914</xmin>
            <ymin>261</ymin>
            <xmax>1036</xmax>
            <ymax>386</ymax>
        </bndbox>
    </object>
    <object>
        <name>overbed_table</name>
        <difficult>0</difficult>
        <bndbox>
            <xmin>19</xmin>
            <ymin>364</ymin>
            <xmax>282</xmax>
            <ymax>489</ymax>
        </bndbox>
    </object>
    <object>
        <name>chair</name>
        <difficult>0</difficult>
        <bndbox>
            <xmin>1</xmin>
            <ymin>228</ymin>
            <xmax>246</xmax>
            <ymax>506</ymax>
        </bndbox>
    </object>
    <object>
        <name>hospital_bed</name>
        <difficult>0</difficult>
        <bndbox>
            <xmin>1</xmin>
            <ymin>302</ymin>
            <xmax>656</xmax>
            <ymax>720</ymax>
        </bndbox>
    </object>
</annotation>