<annotation>
    <folder>image</folder>
    <filename>image_706.jpg</filename>
    <size>
        <width>1280</width>
        <height>720</height>
        <depth>3</depth>
    </size>
    <object>
        <name>bedside_monitor</name>
        <difficult>0</difficult>
        <bndbox>
            <xmin>303.000000</xmin>
            <ymin>207.000000</ymin>
            <xmax>424.000000</xmax>
            <ymax>379.000000</ymax>
        </bndbox>
    </object>
    <object>
        <name>bedside_monitor</name>
        <difficult>0</difficult>
        <bndbox>
            <xmin>295.000000</xmin>
            <ymin>338.000000</ymin>
            <xmax>404.000000</xmax>
            <ymax>490.000000</ymax>
        </bndbox>
    </object>
    <object>
        <name>bedside_monitor</name>
        <difficult>0</difficult>
        <bndbox>
            <xmin>675.000000</xmin>
            <ymin>128.000000</ymin>
            <xmax>778.000000</xmax>
            <ymax>347.000000</ymax>
        </bndbox>
    </object>
    <object>
        <name>bedside_monitor</name>
        <difficult>0</difficult>
        <bndbox>
            <xmin>863.000000</xmin>
            <ymin>427.000000</ymin>
            <xmax>940.000000</xmax>
            <ymax>484.000000</ymax>
        </bndbox>
    </object>
    <object>
        <name>breathing_tube</name>
        <difficult>0</difficult>
        <bndbox>
            <xmin>166.000000</xmin>
            <ymin>444.000000</ymin>
            <xmax>421.000000</xmax>
            <ymax>720.000000</ymax>
        </bndbox>
    </object>
    <object>
        <name>ventilator</name>
        <difficult>0</difficult>
        <bndbox>
            <xmin>168.868744</xmin>
            <ymin>467.351379</ymin>
            <xmax>523.591370</xmax>
            <ymax>720.000000</ymax>
        </bndbox>
    </object>
    <object>
        <name>surgical_light</name>
        <difficult>0</difficult>
        <bndbox>
            <xmin>913.000000</xmin>
            <ymin>95.000000</ymin>
            <xmax>1180.000000</xmax>
            <ymax>372.000000</ymax>
        </bndbox>
    </object>
</annotation>