<annotation>
    <folder>image</folder>
    <filename>image_4081.jpg</filename>
    <size>
        <width>1280</width>
        <height>720</height>
        <depth>3</depth>
    </size>
    <object>
        <name>utility_cart</name>
        <difficult>0</difficult>
        <bndbox>
            <xmin>432.000000</xmin>
            <ymin>370.000000</ymin>
            <xmax>487.000000</xmax>
            <ymax>472.000000</ymax>
        </bndbox>
    </object>
    <object>
        <name>bedside_monitor</name>
        <difficult>0</difficult>
        <bndbox>
            <xmin>806.000000</xmin>
            <ymin>242.000000</ymin>
            <xmax>858.000000</xmax>
            <ymax>282.000000</ymax>
        </bndbox>
    </object>
    <object>
        <name>medical_drawer</name>
        <difficult>0</difficult>
        <bndbox>
            <xmin>791.000000</xmin>
            <ymin>439.000000</ymin>
            <xmax>1033.000000</xmax>
            <ymax>637.000000</ymax>
        </bndbox>
    </object>
    <object>
        <name>surgical_light</name>
        <difficult>0</difficult>
        <bndbox>
            <xmin>72.000000</xmin>
            <ymin>13.000000</ymin>
            <xmax>333.000000</xmax>
            <ymax>157.000000</ymax>
        </bndbox>
    </object>
    <object>
        <name>iv_pole</name>
        <difficult>0</difficult>
        <bndbox>
            <xmin>620.000000</xmin>
            <ymin>96.000000</ymin>
            <xmax>692.000000</xmax>
            <ymax>432.000000</ymax>
        </bndbox>
    </object>
    <object>
        <name>operating_bed</name>
        <difficult>0</difficult>
        <bndbox>
            <xmin>130.000000</xmin>
            <ymin>432.000000</ymin>
            <xmax>607.000000</xmax>
            <ymax>716.000000</ymax>
        </bndbox>
    </object>
    <object>
        <name>computer</name>
        <difficult>0</difficult>
        <bndbox>
            <xmin>1022.000000</xmin>
            <ymin>319.000000</ymin>
            <xmax>1228.000000</xmax>
            <ymax>529.000000</ymax>
        </bndbox>
    </object>
    <object>
        <name>mouse</name>
        <difficult>0</difficult>
        <bndbox>
            <xmin>1024.000000</xmin>
            <ymin>585.000000</ymin>
            <xmax>1096.000000</xmax>
            <ymax>626.000000</ymax>
        </bndbox>
    </object>
    <object>
        <name>keyboard</name>
        <difficult>0</difficult>
        <bndbox>
            <xmin>938.000000</xmin>
            <ymin>489.000000</ymin>
            <xmax>1100.000000</xmax>
            <ymax>579.000000</ymax>
        </bndbox>
    </object>
    <object>
        <name>breathing_tube</name>
        <difficult>0</difficult>
        <bndbox>
            <xmin>647.000000</xmin>
            <ymin>389.000000</ymin>
            <xmax>766.000000</xmax>
            <ymax>640.000000</ymax>
        </bndbox>
    </object>
    <object>
        <name>bedside_monitor</name>
        <difficult>0</difficult>
        <bndbox>
            <xmin>682.000000</xmin>
            <ymin>266.000000</ymin>
            <xmax>794.000000</xmax>
            <ymax>350.000000</ymax>
        </bndbox>
    </object>
    <object>
        <name>chair</name>
        <difficult>0</difficult>
        <bndbox>
            <xmin>765.000000</xmin>
            <ymin>458.000000</ymin>
            <xmax>1082.000000</xmax>
            <ymax>720.000000</ymax>
        </bndbox>
    </object>
    <object>
        <name>waste_bin</name>
        <difficult>0</difficult>
        <bndbox>
            <xmin>1109.000000</xmin>
            <ymin>554.000000</ymin>
            <xmax>1267.000000</xmax>
            <ymax>720.000000</ymax>
        </bndbox>
    </object>
    <object>
        <name>utility_cart</name>
        <difficult>0</difficult>
        <bndbox>
            <xmin>448.000000</xmin>
            <ymin>376.000000</ymin>
            <xmax>641.000000</xmax>
            <ymax>466.000000</ymax>
        </bndbox>
    </object>
    <object>
        <name>surgical_light</name>
        <difficult>0</difficult>
        <bndbox>
            <xmin>244.000000</xmin>
            <ymin>1.000000</ymin>
            <xmax>559.000000</xmax>
            <ymax>78.000000</ymax>
        </bndbox>
    </object>
    <object>
        <name>cabinet</name>
        <difficult>0</difficult>
        <bndbox>
            <xmin>1.000000</xmin>
            <ymin>216.000000</ymin>
            <xmax>352.000000</xmax>
            <ymax>515.000000</ymax>
        </bndbox>
    </object>
    <object>
        <name>utility_cart</name>
        <difficult>0</difficult>
        <bndbox>
            <xmin>101.000000</xmin>
            <ymin>410.000000</ymin>
            <xmax>255.000000</xmax>
            <ymax>643.000000</ymax>
        </bndbox>
    </object>
</annotation>