<annotation>
    <folder>image_cleaned</folder>
    <filename>Admission to A Hospital Ward - Learning Disabilities Version 397.jpg</filename>
    <size>
        <width>1280</width>
        <height>720</height>
        <depth>3</depth>
    </size>
    <object>
        <name>utility_cart</name>
        <difficult>0</difficult>
        <bndbox>
            <xmin>208</xmin>
            <ymin>450</ymin>
            <xmax>970</xmax>
            <ymax>720</ymax>
        </bndbox>
    </object>
    <object>
        <name>staff</name>
        <difficult>0</difficult>
        <bndbox>
            <xmin>483</xmin>
            <ymin>61</ymin>
            <xmax>782</xmax>
            <ymax>571</ymax>
        </bndbox>
    </object>
    <object>
        <name>staff</name>
        <difficult>0</difficult>
        <bndbox>
            <xmin>197</xmin>
            <ymin>131</ymin>
            <xmax>384</xmax>
            <ymax>523</ymax>
        </bndbox>
    </object>
    <object>
        <name>visitor</name>
        <difficult>0</difficult>
        <bndbox>
            <xmin>321</xmin>
            <ymin>151</ymin>
            <xmax>391</xmax>
            <ymax>361</ymax>
        </bndbox>
    </object>
    <object>
        <name>visitor</name>
        <difficult>0</difficult>
        <bndbox>
            <xmin>174</xmin>
            <ymin>100</ymin>
            <xmax>282</xmax>
            <ymax>352</ymax>
        </bndbox>
    </object>
    <object>
        <name>door_handle</name>
        <difficult>0</difficult>
        <bndbox>
            <xmin>64</xmin>
            <ymin>367</ymin>
            <xmax>93</xmax>
            <ymax>386</ymax>
        </bndbox>
    </object>
    <object>
        <name>dispenser</name>
        <difficult>0</difficult>
        <bndbox>
            <xmin>639</xmin>
            <ymin>59</ymin>
            <xmax>749</xmax>
            <ymax>238</ymax>
        </bndbox>
    </object>
    <object>
        <name>hallway_assist_bar</name>
        <difficult>0</difficult>
        <bndbox>
            <xmin>803</xmin>
            <ymin>451</ymin>
            <xmax>1280</xmax>
            <ymax>572</ymax>
        </bndbox>
    </object>
</annotation>