<annotation>
    <folder>image_cleaned</folder>
    <filename>Birth Center Tour 2020 - Valley Medical Center 191.jpg</filename>
    <size>
        <width>1280</width>
        <height>720</height>
        <depth>3</depth>
    </size>
    <object>
        <name>curtain</name>
        <difficult>0</difficult>
        <bndbox>
            <xmin>270</xmin>
            <ymin>2</ymin>
            <xmax>376</xmax>
            <ymax>596</ymax>
        </bndbox>
    </object>
    <object>
        <name>restroom_assist_bar</name>
        <difficult>0</difficult>
        <bndbox>
            <xmin>679</xmin>
            <ymin>225</ymin>
            <xmax>1280</xmax>
            <ymax>417</ymax>
        </bndbox>
    </object>
    <object>
        <name>restroom_assist_bar</name>
        <difficult>0</difficult>
        <bndbox>
            <xmin>667</xmin>
            <ymin>269</ymin>
            <xmax>1280</xmax>
            <ymax>501</ymax>
        </bndbox>
    </object>
    <object>
        <name>faucet</name>
        <difficult>0</difficult>
        <bndbox>
            <xmin>553</xmin>
            <ymin>319</ymin>
            <xmax>617</xmax>
            <ymax>385</ymax>
        </bndbox>
    </object>
    <object>
        <name>restroom_assist_bar</name>
        <difficult>0</difficult>
        <bndbox>
            <xmin>386</xmin>
            <ymin>30</ymin>
            <xmax>431</xmax>
            <ymax>215</ymax>
        </bndbox>
    </object>
    <object>
        <name>restroom_assist_bar</name>
        <difficult>0</difficult>
        <bndbox>
            <xmin>410</xmin>
            <ymin>270</ymin>
            <xmax>647</xmax>
            <ymax>352</ymax>
        </bndbox>
    </object>
    <object>
        <name>restroom_assist_bar</name>
        <difficult>0</difficult>
        <bndbox>
            <xmin>543</xmin>
            <ymin>1</ymin>
            <xmax>574</xmax>
            <ymax>104</ymax>
        </bndbox>
    </object>
    <object>
        <name>dispenser</name>
        <difficult>0</difficult>
        <bndbox>
            <xmin>1141</xmin>
            <ymin>1</ymin>
            <xmax>1280</xmax>
            <ymax>230</ymax>
        </bndbox>
    </object>
    <object>
        <name>faucet</name>
        <difficult>0</difficult>
        <bndbox>
            <xmin>530</xmin>
            <ymin>195</ymin>
            <xmax>591</xmax>
            <ymax>270</ymax>
        </bndbox>
    </object>
</annotation>