<annotation>
    <folder>image_cleaned</folder>
    <filename>Hallway54.jpg</filename>
    <size>
        <width>1480</width>
        <height>800</height>
        <depth>3</depth>
    </size>
    <object>
        <name>hallway_assist_bar</name>
        <difficult>0</difficult>
        <bndbox>
            <xmin>798</xmin>
            <ymin>363</ymin>
            <xmax>817</xmax>
            <ymax>380</ymax>
        </bndbox>
    </object>
    <object>
        <name>hallway_assist_bar</name>
        <difficult>0</difficult>
        <bndbox>
            <xmin>618</xmin>
            <ymin>375</ymin>
            <xmax>642</xmax>
            <ymax>387</ymax>
        </bndbox>
    </object>
    <object>
        <name>hallway_assist_bar</name>
        <difficult>0</difficult>
        <bndbox>
            <xmin>536</xmin>
            <ymin>380</ymin>
            <xmax>614</xmax>
            <ymax>408</ymax>
        </bndbox>
    </object>
    <object>
        <name>chair</name>
        <difficult>0</difficult>
        <bndbox>
            <xmin>297</xmin>
            <ymin>421</ymin>
            <xmax>555</xmax>
            <ymax>659</ymax>
        </bndbox>
    </object>
    <object>
        <name>chair</name>
        <difficult>0</difficult>
        <bndbox>
            <xmin>649</xmin>
            <ymin>366</ymin>
            <xmax>692</xmax>
            <ymax>419</ymax>
        </bndbox>
    </object>
    <object>
        <name>hospital_bed</name>
        <difficult>0</difficult>
        <bndbox>
            <xmin>907</xmin>
            <ymin>344</ymin>
            <xmax>1265</xmax>
            <ymax>676</ymax>
        </bndbox>
    </object>
    <object>
        <name>foot_board</name>
        <difficult>0</difficult>
        <bndbox>
            <xmin>970</xmin>
            <ymin>393</ymin>
            <xmax>1241</xmax>
            <ymax>549</ymax>
        </bndbox>
    </object>
    <object>
        <name>bedrail</name>
        <difficult>0</difficult>
        <bndbox>
            <xmin>907</xmin>
            <ymin>343</ymin>
            <xmax>935</xmax>
            <ymax>514</ymax>
        </bndbox>
    </object>
    <object>
        <name>bedrail</name>
        <difficult>0</difficult>
        <bndbox>
            <xmin>929</xmin>
            <ymin>501</ymin>
            <xmax>972</xmax>
            <ymax>641</ymax>
        </bndbox>
    </object>
    <object>
        <name>hospital_bed</name>
        <difficult>0</difficult>
        <bndbox>
            <xmin>821</xmin>
            <ymin>347</ymin>
            <xmax>902</xmax>
            <ymax>485</ymax>
        </bndbox>
    </object>
    <object>
        <name>bedrail</name>
        <difficult>0</difficult>
        <bndbox>
            <xmin>820</xmin>
            <ymin>348</ymin>
            <xmax>832</xmax>
            <ymax>425</ymax>
        </bndbox>
    </object>
    <object>
        <name>foot_board</name>
        <difficult>0</difficult>
        <bndbox>
            <xmin>833</xmin>
            <ymin>366</ymin>
            <xmax>908</xmax>
            <ymax>429</ymax>
        </bndbox>
    </object>
    <object>
        <name>door_handle</name>
        <difficult>0</difficult>
        <bndbox>
            <xmin>1335</xmin>
            <ymin>425</ymin>
            <xmax>1372</xmax>
            <ymax>471</ymax>
        </bndbox>
    </object>
    <object>
        <name>door_handle</name>
        <difficult>0</difficult>
        <bndbox>
            <xmin>146</xmin>
            <ymin>427</ymin>
            <xmax>174</xmax>
            <ymax>481</ymax>
        </bndbox>
    </object>
</annotation>