<annotation>
    <folder>image_cleaned</folder>
    <filename>Blacktown Hospital Maternity Tour 208.jpg</filename>
    <size>
        <width>1280</width>
        <height>720</height>
        <depth>3</depth>
    </size>
    <object>
        <name>staff</name>
        <difficult>0</difficult>
        <bndbox>
            <xmin>212</xmin>
            <ymin>47</ymin>
            <xmax>745</xmax>
            <ymax>720</ymax>
        </bndbox>
    </object>
    <object>
        <name>mouse</name>
        <difficult>0</difficult>
        <bndbox>
            <xmin>794</xmin>
            <ymin>570</ymin>
            <xmax>874</xmax>
            <ymax>627</ymax>
        </bndbox>
    </object>
    <object>
        <name>keyboard</name>
        <difficult>0</difficult>
        <bndbox>
            <xmin>949</xmin>
            <ymin>528</ymin>
            <xmax>1217</xmax>
            <ymax>616</ymax>
        </bndbox>
    </object>
    <object>
        <name>computer</name>
        <difficult>0</difficult>
        <bndbox>
            <xmin>1146</xmin>
            <ymin>138</ymin>
            <xmax>1277</xmax>
            <ymax>530</ymax>
        </bndbox>
    </object>
    <object>
        <name>telephone</name>
        <difficult>0</difficult>
        <bndbox>
            <xmin>970</xmin>
            <ymin>571</ymin>
            <xmax>1204</xmax>
            <ymax>691</ymax>
        </bndbox>
    </object>
    <object>
        <name>countertop</name>
        <difficult>0</difficult>
        <bndbox>
            <xmin>1</xmin>
            <ymin>481</ymin>
            <xmax>220</xmax>
            <ymax>582</ymax>
        </bndbox>
    </object>
</annotation>