<annotation>
    <folder>image_cleaned</folder>
    <filename>Greer Hospital Tour 248.jpg</filename>
    <size>
        <width>1280</width>
        <height>720</height>
        <depth>3</depth>
    </size>
    <object>
        <name>light_switch</name>
        <difficult>0</difficult>
        <bndbox>
            <xmin>679</xmin>
            <ymin>169</ymin>
            <xmax>703</xmax>
            <ymax>216</ymax>
        </bndbox>
    </object>
    <object>
        <name>sofa</name>
        <difficult>0</difficult>
        <bndbox>
            <xmin>971</xmin>
            <ymin>398</ymin>
            <xmax>1280</xmax>
            <ymax>655</ymax>
        </bndbox>
    </object>
    <object>
        <name>bedrail</name>
        <difficult>0</difficult>
        <bndbox>
            <xmin>75</xmin>
            <ymin>352</ymin>
            <xmax>138</xmax>
            <ymax>720</ymax>
        </bndbox>
    </object>
    <object>
        <name>bedrail</name>
        <difficult>0</difficult>
        <bndbox>
            <xmin>546</xmin>
            <ymin>333</ymin>
            <xmax>690</xmax>
            <ymax>615</ymax>
        </bndbox>
    </object>
    <object>
        <name>hospital_bed</name>
        <difficult>0</difficult>
        <bndbox>
            <xmin>70</xmin>
            <ymin>329</ymin>
            <xmax>737</xmax>
            <ymax>720</ymax>
        </bndbox>
    </object>
    <object>
        <name>patient</name>
        <difficult>0</difficult>
        <bndbox>
            <xmin>242</xmin>
            <ymin>233</ymin>
            <xmax>604</xmax>
            <ymax>720</ymax>
        </bndbox>
    </object>
    <object>
        <name>iv_pole</name>
        <difficult>0</difficult>
        <bndbox>
            <xmin>425</xmin>
            <ymin>208</ymin>
            <xmax>472</xmax>
            <ymax>254</ymax>
        </bndbox>
    </object>
    <object>
        <name>infusion_pump</name>
        <difficult>0</difficult>
        <bndbox>
            <xmin>612</xmin>
            <ymin>263</ymin>
            <xmax>706</xmax>
            <ymax>362</ymax>
        </bndbox>
    </object>
    <object>
        <name>staff</name>
        <difficult>0</difficult>
        <bndbox>
            <xmin>493</xmin>
            <ymin>72</ymin>
            <xmax>956</xmax>
            <ymax>697</ymax>
        </bndbox>
    </object>
    <object>
        <name>curtain</name>
        <difficult>0</difficult>
        <bndbox>
            <xmin>1078</xmin>
            <ymin>1</ymin>
            <xmax>1280</xmax>
            <ymax>368</ymax>
        </bndbox>
    </object>
    <object>
        <name>light_switch</name>
        <difficult>0</difficult>
        <bndbox>
            <xmin>85</xmin>
            <ymin>180</ymin>
            <xmax>118</xmax>
            <ymax>233</ymax>
        </bndbox>
    </object>
    <object>
        <name>iv_pole</name>
        <difficult>0</difficult>
        <bndbox>
            <xmin>636</xmin>
            <ymin>1</ymin>
            <xmax>659</xmax>
            <ymax>264</ymax>
        </bndbox>
    </object>
</annotation>