<annotation>
    <folder>image_cleaned</folder>
    <filename>Consulting110.jpg</filename>
    <size>
        <width>768</width>
        <height>768</height>
        <depth>3</depth>
    </size>
    <object>
        <name>cabinet</name>
        <difficult>0</difficult>
        <bndbox>
            <xmin>325</xmin>
            <ymin>283</ymin>
            <xmax>657</xmax>
            <ymax>369</ymax>
        </bndbox>
    </object>
    <object>
        <name>chair</name>
        <difficult>0</difficult>
        <bndbox>
            <xmin>523</xmin>
            <ymin>526</ymin>
            <xmax>681</xmax>
            <ymax>768</ymax>
        </bndbox>
    </object>
    <object>
        <name>chair</name>
        <difficult>0</difficult>
        <bndbox>
            <xmin>492</xmin>
            <ymin>437</ymin>
            <xmax>588</xmax>
            <ymax>585</ymax>
        </bndbox>
    </object>
    <object>
        <name>computer</name>
        <difficult>0</difficult>
        <bndbox>
            <xmin>519</xmin>
            <ymin>394</ymin>
            <xmax>626</xmax>
            <ymax>456</ymax>
        </bndbox>
    </object>
    <object>
        <name>countertop</name>
        <difficult>0</difficult>
        <bndbox>
            <xmin>341</xmin>
            <ymin>432</ymin>
            <xmax>657</xmax>
            <ymax>492</ymax>
        </bndbox>
    </object>
    <object>
        <name>sink</name>
        <difficult>0</difficult>
        <bndbox>
            <xmin>380</xmin>
            <ymin>420</ymin>
            <xmax>425</xmax>
            <ymax>442</ymax>
        </bndbox>
    </object>
    <object>
        <name>faucet</name>
        <difficult>0</difficult>
        <bndbox>
            <xmin>406</xmin>
            <ymin>403</ymin>
            <xmax>415</xmax>
            <ymax>422</ymax>
        </bndbox>
    </object>
    <object>
        <name>exam_table</name>
        <difficult>0</difficult>
        <bndbox>
            <xmin>64</xmin>
            <ymin>452</ymin>
            <xmax>396</xmax>
            <ymax>768</ymax>
        </bndbox>
    </object>
    <object>
        <name>mouse</name>
        <difficult>0</difficult>
        <bndbox>
            <xmin>594</xmin>
            <ymin>450</ymin>
            <xmax>605</xmax>
            <ymax>456</ymax>
        </bndbox>
    </object>
</annotation>