<annotation>
    <folder>image_cleaned</folder>
    <filename>Greer Hospital Tour 146.jpg</filename>
    <size>
        <width>1280</width>
        <height>720</height>
        <depth>3</depth>
    </size>
    <object>
        <name>bedside_table</name>
        <difficult>0</difficult>
        <bndbox>
            <xmin>536</xmin>
            <ymin>302</ymin>
            <xmax>843</xmax>
            <ymax>631</ymax>
        </bndbox>
    </object>
    <object>
        <name>patient</name>
        <difficult>0</difficult>
        <bndbox>
            <xmin>551</xmin>
            <ymin>220</ymin>
            <xmax>1094</xmax>
            <ymax>720</ymax>
        </bndbox>
    </object>
    <object>
        <name>bedrail</name>
        <difficult>0</difficult>
        <bndbox>
            <xmin>906</xmin>
            <ymin>462</ymin>
            <xmax>1244</xmax>
            <ymax>720</ymax>
        </bndbox>
    </object>
    <object>
        <name>bedrail</name>
        <difficult>0</difficult>
        <bndbox>
            <xmin>1</xmin>
            <ymin>404</ymin>
            <xmax>690</xmax>
            <ymax>720</ymax>
        </bndbox>
    </object>
    <object>
        <name>hospital_bed</name>
        <difficult>0</difficult>
        <bndbox>
            <xmin>97</xmin>
            <ymin>327</ymin>
            <xmax>1206</xmax>
            <ymax>720</ymax>
        </bndbox>
    </object>
    <object>
        <name>iv_pole</name>
        <difficult>0</difficult>
        <bndbox>
            <xmin>836</xmin>
            <ymin>164</ymin>
            <xmax>897</xmax>
            <ymax>342</ymax>
        </bndbox>
    </object>
    <object>
        <name>staff</name>
        <difficult>0</difficult>
        <bndbox>
            <xmin>223</xmin>
            <ymin>1</ymin>
            <xmax>612</xmax>
            <ymax>720</ymax>
        </bndbox>
    </object>
    <object>
        <name>telephone</name>
        <difficult>0</difficult>
        <bndbox>
            <xmin>760</xmin>
            <ymin>275</ymin>
            <xmax>826</xmax>
            <ymax>318</ymax>
        </bndbox>
    </object>
    <object>
        <name>handle</name>
        <difficult>0</difficult>
        <bndbox>
            <xmin>616</xmin>
            <ymin>383</ymin>
            <xmax>634</xmax>
            <ymax>405</ymax>
        </bndbox>
    </object>
    <object>
        <name>handle</name>
        <difficult>0</difficult>
        <bndbox>
            <xmin>626</xmin>
            <ymin>486</ymin>
            <xmax>647</xmax>
            <ymax>510</ymax>
        </bndbox>
    </object>
    <object>
        <name>iv_pole</name>
        <difficult>0</difficult>
        <bndbox>
            <xmin>887</xmin>
            <ymin>1</ymin>
            <xmax>905</xmax>
            <ymax>228</ymax>
        </bndbox>
    </object>
    <object>
        <name>iv_pole</name>
        <difficult>0</difficult>
        <bndbox>
            <xmin>947</xmin>
            <ymin>1</ymin>
            <xmax>969</xmax>
            <ymax>240</ymax>
        </bndbox>
    </object>
</annotation>