<annotation>
    <folder>image_cleaned</folder>
    <filename>Geneva General Hospital Virtual Tour 2014 478.jpg</filename>
    <size>
        <width>1280</width>
        <height>720</height>
        <depth>3</depth>
    </size>
    <object>
        <name>table</name>
        <difficult>0</difficult>
        <bndbox>
            <xmin>16</xmin>
            <ymin>562</ymin>
            <xmax>308</xmax>
            <ymax>720</ymax>
        </bndbox>
    </object>
    <object>
        <name>chair</name>
        <difficult>0</difficult>
        <bndbox>
            <xmin>78</xmin>
            <ymin>342</ymin>
            <xmax>392</xmax>
            <ymax>717</ymax>
        </bndbox>
    </object>
    <object>
        <name>chair</name>
        <difficult>0</difficult>
        <bndbox>
            <xmin>203</xmin>
            <ymin>293</ymin>
            <xmax>473</xmax>
            <ymax>518</ymax>
        </bndbox>
    </object>
    <object>
        <name>chair</name>
        <difficult>0</difficult>
        <bndbox>
            <xmin>345</xmin>
            <ymin>266</ymin>
            <xmax>534</xmax>
            <ymax>475</ymax>
        </bndbox>
    </object>
    <object>
        <name>chair</name>
        <difficult>0</difficult>
        <bndbox>
            <xmin>449</xmin>
            <ymin>255</ymin>
            <xmax>620</xmax>
            <ymax>436</ymax>
        </bndbox>
    </object>
    <object>
        <name>chair</name>
        <difficult>0</difficult>
        <bndbox>
            <xmin>610</xmin>
            <ymin>238</ymin>
            <xmax>763</xmax>
            <ymax>409</ymax>
        </bndbox>
    </object>
    <object>
        <name>table</name>
        <difficult>0</difficult>
        <bndbox>
            <xmin>925</xmin>
            <ymin>325</ymin>
            <xmax>1244</xmax>
            <ymax>409</ymax>
        </bndbox>
    </object>
    <object>
        <name>table</name>
        <difficult>0</difficult>
        <bndbox>
            <xmin>623</xmin>
            <ymin>535</ymin>
            <xmax>1280</xmax>
            <ymax>720</ymax>
        </bndbox>
    </object>
    <object>
        <name>chair</name>
        <difficult>0</difficult>
        <bndbox>
            <xmin>497</xmin>
            <ymin>486</ymin>
            <xmax>696</xmax>
            <ymax>720</ymax>
        </bndbox>
    </object>
    <object>
        <name>chair</name>
        <difficult>0</difficult>
        <bndbox>
            <xmin>877</xmin>
            <ymin>305</ymin>
            <xmax>950</xmax>
            <ymax>528</ymax>
        </bndbox>
    </object>
    <object>
        <name>chair</name>
        <difficult>0</difficult>
        <bndbox>
            <xmin>901</xmin>
            <ymin>352</ymin>
            <xmax>1062</xmax>
            <ymax>539</ymax>
        </bndbox>
    </object>
    <object>
        <name>chair</name>
        <difficult>0</difficult>
        <bndbox>
            <xmin>1096</xmin>
            <ymin>366</ymin>
            <xmax>1280</xmax>
            <ymax>609</ymax>
        </bndbox>
    </object>
    <object>
        <name>chair</name>
        <difficult>0</difficult>
        <bndbox>
            <xmin>804</xmin>
            <ymin>223</ymin>
            <xmax>891</xmax>
            <ymax>368</ymax>
        </bndbox>
    </object>
    <object>
        <name>chair</name>
        <difficult>0</difficult>
        <bndbox>
            <xmin>1067</xmin>
            <ymin>302</ymin>
            <xmax>1188</xmax>
            <ymax>438</ymax>
        </bndbox>
    </object>
    <object>
        <name>chair</name>
        <difficult>0</difficult>
        <bndbox>
            <xmin>945</xmin>
            <ymin>477</ymin>
            <xmax>1211</xmax>
            <ymax>589</ymax>
        </bndbox>
    </object>
    <object>
        <name>chair</name>
        <difficult>0</difficult>
        <bndbox>
            <xmin>1</xmin>
            <ymin>600</ymin>
            <xmax>180</xmax>
            <ymax>720</ymax>
        </bndbox>
    </object>
    <object>
        <name>table</name>
        <difficult>0</difficult>
        <bndbox>
            <xmin>579</xmin>
            <ymin>324</ymin>
            <xmax>691</xmax>
            <ymax>391</ymax>
        </bndbox>
    </object>
</annotation>