<annotation>
    <folder>image_cleaned</folder>
    <filename>Derby Teaching Hospitals Maternity Tour 075.jpg</filename>
    <size>
        <width>1280</width>
        <height>720</height>
        <depth>3</depth>
    </size>
    <object>
        <name>light_switch</name>
        <difficult>0</difficult>
        <bndbox>
            <xmin>565</xmin>
            <ymin>89</ymin>
            <xmax>614</xmax>
            <ymax>130</ymax>
        </bndbox>
    </object>
    <object>
        <name>chair</name>
        <difficult>0</difficult>
        <bndbox>
            <xmin>669</xmin>
            <ymin>189</ymin>
            <xmax>992</xmax>
            <ymax>624</ymax>
        </bndbox>
    </object>
    <object>
        <name>chair</name>
        <difficult>0</difficult>
        <bndbox>
            <xmin>523</xmin>
            <ymin>264</ymin>
            <xmax>826</xmax>
            <ymax>688</ymax>
        </bndbox>
    </object>
    <object>
        <name>table</name>
        <difficult>0</difficult>
        <bndbox>
            <xmin>275</xmin>
            <ymin>426</ymin>
            <xmax>681</xmax>
            <ymax>720</ymax>
        </bndbox>
    </object>
    <object>
        <name>chair</name>
        <difficult>0</difficult>
        <bndbox>
            <xmin>1</xmin>
            <ymin>315</ymin>
            <xmax>444</xmax>
            <ymax>720</ymax>
        </bndbox>
    </object>
    <object>
        <name>chair</name>
        <difficult>0</difficult>
        <bndbox>
            <xmin>979</xmin>
            <ymin>246</ymin>
            <xmax>1243</xmax>
            <ymax>605</ymax>
        </bndbox>
    </object>
    <object>
        <name>chair</name>
        <difficult>0</difficult>
        <bndbox>
            <xmin>1222</xmin>
            <ymin>272</ymin>
            <xmax>1280</xmax>
            <ymax>617</ymax>
        </bndbox>
    </object>
</annotation>