<annotation>
    <folder>image_cleaned</folder>
    <filename>Hallway50.jpg</filename>
    <size>
        <width>1600</width>
        <height>900</height>
        <depth>3</depth>
    </size>
    <object>
        <name>dispenser</name>
        <difficult>0</difficult>
        <bndbox>
            <xmin>225</xmin>
            <ymin>464</ymin>
            <xmax>339</xmax>
            <ymax>503</ymax>
        </bndbox>
    </object>
    <object>
        <name>dispenser</name>
        <difficult>0</difficult>
        <bndbox>
            <xmin>158</xmin>
            <ymin>371</ymin>
            <xmax>210</xmax>
            <ymax>497</ymax>
        </bndbox>
    </object>
    <object>
        <name>hallway_assist_bar</name>
        <difficult>0</difficult>
        <bndbox>
            <xmin>1214</xmin>
            <ymin>492</ymin>
            <xmax>1266</xmax>
            <ymax>589</ymax>
        </bndbox>
    </object>
    <object>
        <name>computer</name>
        <difficult>0</difficult>
        <bndbox>
            <xmin>1147</xmin>
            <ymin>291</ymin>
            <xmax>1241</xmax>
            <ymax>430</ymax>
        </bndbox>
    </object>
    <object>
        <name>computer</name>
        <difficult>0</difficult>
        <bndbox>
            <xmin>1026</xmin>
            <ymin>288</ymin>
            <xmax>1117</xmax>
            <ymax>414</ymax>
        </bndbox>
    </object>
    <object>
        <name>hallway_assist_bar</name>
        <difficult>0</difficult>
        <bndbox>
            <xmin>1389</xmin>
            <ymin>617</ymin>
            <xmax>1595</xmax>
            <ymax>899</ymax>
        </bndbox>
    </object>
    <object>
        <name>staff</name>
        <difficult>0</difficult>
        <bndbox>
            <xmin>655</xmin>
            <ymin>138</ymin>
            <xmax>927</xmax>
            <ymax>889</ymax>
        </bndbox>
    </object>
    <object>
        <name>computer</name>
        <difficult>0</difficult>
        <bndbox>
            <xmin>444</xmin>
            <ymin>276</ymin>
            <xmax>618</xmax>
            <ymax>377</ymax>
        </bndbox>
    </object>
    <object>
        <name>chair</name>
        <difficult>0</difficult>
        <bndbox>
            <xmin>402</xmin>
            <ymin>429</ymin>
            <xmax>631</xmax>
            <ymax>738</ymax>
        </bndbox>
    </object>
    <object>
        <name>waste_bin</name>
        <difficult>0</difficult>
        <bndbox>
            <xmin>1</xmin>
            <ymin>712</ymin>
            <xmax>252</xmax>
            <ymax>900</ymax>
        </bndbox>
    </object>
    <object>
        <name>waste_bin</name>
        <difficult>0</difficult>
        <bndbox>
            <xmin>223</xmin>
            <ymin>590</ymin>
            <xmax>396</xmax>
            <ymax>848</ymax>
        </bndbox>
    </object>
    <object>
        <name>utility_cart</name>
        <difficult>0</difficult>
        <bndbox>
            <xmin>200</xmin>
            <ymin>482</ymin>
            <xmax>396</xmax>
            <ymax>900</ymax>
        </bndbox>
    </object>
    <object>
        <name>dispenser</name>
        <difficult>0</difficult>
        <bndbox>
            <xmin>196</xmin>
            <ymin>238</ymin>
            <xmax>250</xmax>
            <ymax>425</ymax>
        </bndbox>
    </object>
</annotation>