<annotation>
    <folder>image_cleaned</folder>
    <filename>my-hospital-ward-tour 026.jpg</filename>
    <size>
        <width>1280</width>
        <height>720</height>
        <depth>3</depth>
    </size>
    <object>
        <name>chair</name>
        <difficult>0</difficult>
        <bndbox>
            <xmin>526</xmin>
            <ymin>253</ymin>
            <xmax>716</xmax>
            <ymax>379</ymax>
        </bndbox>
    </object>
    <object>
        <name>chair</name>
        <difficult>0</difficult>
        <bndbox>
            <xmin>231</xmin>
            <ymin>249</ymin>
            <xmax>459</xmax>
            <ymax>720</ymax>
        </bndbox>
    </object>
    <object>
        <name>chair</name>
        <difficult>0</difficult>
        <bndbox>
            <xmin>52</xmin>
            <ymin>248</ymin>
            <xmax>256</xmax>
            <ymax>660</ymax>
        </bndbox>
    </object>
    <object>
        <name>chair</name>
        <difficult>0</difficult>
        <bndbox>
            <xmin>19</xmin>
            <ymin>250</ymin>
            <xmax>235</xmax>
            <ymax>576</ymax>
        </bndbox>
    </object>
</annotation>