<annotation>
    <folder>image</folder>
    <filename>image_2169.jpg</filename>
    <size>
        <width>1280</width>
        <height>720</height>
        <depth>3</depth>
    </size>
    <object>
        <name>counter</name>
        <difficult>0</difficult>
        <bndbox>
            <xmin>1.000000</xmin>
            <ymin>374.000000</ymin>
            <xmax>112.000000</xmax>
            <ymax>480.000000</ymax>
        </bndbox>
    </object>
    <object>
        <name>countertop</name>
        <difficult>0</difficult>
        <bndbox>
            <xmin>628.000000</xmin>
            <ymin>511.000000</ymin>
            <xmax>1061.000000</xmax>
            <ymax>596.000000</ymax>
        </bndbox>
    </object>
    <object>
        <name>TV</name>
        <difficult>0</difficult>
        <bndbox>
            <xmin>919.000000</xmin>
            <ymin>245.000000</ymin>
            <xmax>1061.000000</xmax>
            <ymax>362.000000</ymax>
        </bndbox>
    </object>
    <object>
        <name>counter</name>
        <difficult>0</difficult>
        <bndbox>
            <xmin>214.000000</xmin>
            <ymin>459.000000</ymin>
            <xmax>1061.000000</xmax>
            <ymax>720.000000</ymax>
        </bndbox>
    </object>
    <object>
        <name>dispenser</name>
        <difficult>0</difficult>
        <bndbox>
            <xmin>1119.000000</xmin>
            <ymin>421.000000</ymin>
            <xmax>1190.000000</xmax>
            <ymax>648.000000</ymax>
        </bndbox>
    </object>
    <object>
        <name>chair</name>
        <difficult>0</difficult>
        <bndbox>
            <xmin>243.000000</xmin>
            <ymin>432.000000</ymin>
            <xmax>405.000000</xmax>
            <ymax>569.000000</ymax>
        </bndbox>
    </object>
    <object>
        <name>counter</name>
        <difficult>0</difficult>
        <bndbox>
            <xmin>238.000000</xmin>
            <ymin>376.000000</ymin>
            <xmax>415.000000</xmax>
            <ymax>473.000000</ymax>
        </bndbox>
    </object>
</annotation>