<annotation>
    <folder>image_cleaned</folder>
    <filename>nurse-doctor-and-female-girl-child-stock-images_csp46902158.jpg</filename>
    <size>
        <width>600</width>
        <height>419</height>
        <depth>3</depth>
    </size>
    <object>
        <name>handle</name>
        <difficult>0</difficult>
        <bndbox>
            <xmin>3</xmin>
            <ymin>50</ymin>
            <xmax>18</xmax>
            <ymax>94</ymax>
        </bndbox>
    </object>
    <object>
        <name>staff</name>
        <difficult>0</difficult>
        <bndbox>
            <xmin>84</xmin>
            <ymin>70</ymin>
            <xmax>260</xmax>
            <ymax>351</ymax>
        </bndbox>
    </object>
    <object>
        <name>staff</name>
        <difficult>0</difficult>
        <bndbox>
            <xmin>346</xmin>
            <ymin>51</ymin>
            <xmax>523</xmax>
            <ymax>348</ymax>
        </bndbox>
    </object>
    <object>
        <name>patient</name>
        <difficult>0</difficult>
        <bndbox>
            <xmin>273</xmin>
            <ymin>68</ymin>
            <xmax>353</xmax>
            <ymax>280</ymax>
        </bndbox>
    </object>
    <object>
        <name>wheel_chair</name>
        <difficult>0</difficult>
        <bndbox>
            <xmin>232</xmin>
            <ymin>85</ymin>
            <xmax>414</xmax>
            <ymax>350</ymax>
        </bndbox>
    </object>
</annotation>