<annotation>
    <folder>image_cleaned</folder>
    <filename>New York Presbyterian Queens Emergency Medicine Residency - Virtual Tour 188.jpg</filename>
    <size>
        <width>1280</width>
        <height>720</height>
        <depth>3</depth>
    </size>
    <object>
        <name>mouse</name>
        <difficult>0</difficult>
        <bndbox>
            <xmin>175</xmin>
            <ymin>666</ymin>
            <xmax>217</xmax>
            <ymax>689</ymax>
        </bndbox>
    </object>
    <object>
        <name>chair</name>
        <difficult>0</difficult>
        <bndbox>
            <xmin>942</xmin>
            <ymin>588</ymin>
            <xmax>1195</xmax>
            <ymax>720</ymax>
        </bndbox>
    </object>
    <object>
        <name>computer</name>
        <difficult>0</difficult>
        <bndbox>
            <xmin>930</xmin>
            <ymin>489</ymin>
            <xmax>1190</xmax>
            <ymax>645</ymax>
        </bndbox>
    </object>
    <object>
        <name>mouse</name>
        <difficult>0</difficult>
        <bndbox>
            <xmin>1211</xmin>
            <ymin>693</ymin>
            <xmax>1252</xmax>
            <ymax>719</ymax>
        </bndbox>
    </object>
    <object>
        <name>telephone</name>
        <difficult>0</difficult>
        <bndbox>
            <xmin>302</xmin>
            <ymin>619</ymin>
            <xmax>452</xmax>
            <ymax>700</ymax>
        </bndbox>
    </object>
    <object>
        <name>chair</name>
        <difficult>0</difficult>
        <bndbox>
            <xmin>1</xmin>
            <ymin>581</ymin>
            <xmax>114</xmax>
            <ymax>720</ymax>
        </bndbox>
    </object>
    <object>
        <name>computer</name>
        <difficult>0</difficult>
        <bndbox>
            <xmin>1</xmin>
            <ymin>432</ymin>
            <xmax>156</xmax>
            <ymax>608</ymax>
        </bndbox>
    </object>
    <object>
        <name>chair</name>
        <difficult>0</difficult>
        <bndbox>
            <xmin>801</xmin>
            <ymin>631</ymin>
            <xmax>906</xmax>
            <ymax>671</ymax>
        </bndbox>
    </object>
    <object>
        <name>computer</name>
        <difficult>0</difficult>
        <bndbox>
            <xmin>121</xmin>
            <ymin>576</ymin>
            <xmax>286</xmax>
            <ymax>665</ymax>
        </bndbox>
    </object>
    <object>
        <name>computer</name>
        <difficult>0</difficult>
        <bndbox>
            <xmin>431</xmin>
            <ymin>536</ymin>
            <xmax>462</xmax>
            <ymax>626</ymax>
        </bndbox>
    </object>
    <object>
        <name>computer</name>
        <difficult>0</difficult>
        <bndbox>
            <xmin>560</xmin>
            <ymin>533</ymin>
            <xmax>580</xmax>
            <ymax>587</ymax>
        </bndbox>
    </object>
    <object>
        <name>computer</name>
        <difficult>0</difficult>
        <bndbox>
            <xmin>536</xmin>
            <ymin>591</ymin>
            <xmax>773</xmax>
            <ymax>669</ymax>
        </bndbox>
    </object>
    <object>
        <name>dispenser</name>
        <difficult>0</difficult>
        <bndbox>
            <xmin>861</xmin>
            <ymin>592</ymin>
            <xmax>900</xmax>
            <ymax>686</ymax>
        </bndbox>
    </object>
    <object>
        <name>dispenser</name>
        <difficult>0</difficult>
        <bndbox>
            <xmin>248</xmin>
            <ymin>586</ymin>
            <xmax>284</xmax>
            <ymax>680</ymax>
        </bndbox>
    </object>
</annotation>